webshotr/__init__.py
webshotr/cli.py
webshotr/exceptions.py
webshotr/webshotr.py
webshotr-1.0.0.dist-info/licenses/LICENSE
webshotr-1.0.0.dist-info/METADATA
webshotr-1.0.0.dist-info/WHEEL
webshotr-1.0.0.dist-info/entry_points.txt
webshotr-1.0.0.dist-info/top_level.txt
webshotr-1.0.0.dist-info/RECORD
