Metadata-Version: 2.4
Name: webshotr
Version: 1.0.0
Summary: A simple and fast website screenshot tool - WebShotr
Home-page: https://github.com/abderrahimghazali/webshotr
Author: AbderrahimGHAZALI
Author-email: AbderrahimGHAZALI <ghazali.abderrahim1@gmail.com>
Project-URL: Homepage, https://github.com/abderrahimghazali/webshotr
Project-URL: Repository, https://github.com/abderrahimghazali/webshotr
Project-URL: Issues, https://github.com/abderrahimghazali/webshotr/issues
Keywords: screenshot,web,automation,playwright,browser,capture
Classifier: Development Status :: 4 - Beta
Classifier: Intended Audience :: Developers
Classifier: License :: OSI Approved :: MIT License
Classifier: Operating System :: OS Independent
Classifier: Programming Language :: Python :: 3
Classifier: Programming Language :: Python :: 3.7
Classifier: Programming Language :: Python :: 3.8
Classifier: Programming Language :: Python :: 3.9
Classifier: Programming Language :: Python :: 3.10
Classifier: Programming Language :: Python :: 3.11
Classifier: Programming Language :: Python :: 3.12
Classifier: Programming Language :: Python :: 3.13
Classifier: Topic :: Internet :: WWW/HTTP :: Browsers
Classifier: Topic :: Multimedia :: Graphics :: Capture :: Screen Capture
Classifier: Topic :: Software Development :: Libraries :: Python Modules
Classifier: Topic :: Utilities
Requires-Python: >=3.7
License-File: LICENSE
Requires-Dist: playwright>=1.40.0
Requires-Dist: Pillow>=9.0.0
Requires-Dist: click>=8.0.0
Requires-Dist: aiofiles>=22.0.0
Dynamic: author
Dynamic: home-page
Dynamic: license-file
Dynamic: requires-python
